mailSenderLib/__init__.py
mailSenderLib/verifySender.py
mailSenderLib-0.0.4.dist-info/METADATA
mailSenderLib-0.0.4.dist-info/WHEEL
mailSenderLib-0.0.4.dist-info/top_level.txt
mailSenderLib-0.0.4.dist-info/RECORD
