Metadata-Version: 2.1
Name: mailSenderLib
Version: 0.0.4
Summary: Эта библиотека позволит Вам легко обновлять эл. почту.
Home-page: https://github.com/borshcode/mailSenderLib.git
Author: BorshCode
Author-email: rechkinnm@yandex.ru
Project-URL: GitHub, https://github.com/borshcode/mailSenderLib
Keywords: mail sender
Classifier: Programming Language :: Python :: 3.11
Classifier: License :: OSI Approved :: MIT License
Classifier: Operating System :: OS Independent
Requires-Python: >=3.6
